sas/__init__.py
sas/api.py
sas/data.py
sas/sas_batch.py
sas/sas_cheapest.py
sas/sas_monthly.py
sas/types.py
sas/utils.py
tests/__init__.py
tests/test_api.py
sas_prices_py-0.1.2.dist-info/LICENSE
sas_prices_py-0.1.2.dist-info/METADATA
sas_prices_py-0.1.2.dist-info/WHEEL
sas_prices_py-0.1.2.dist-info/top_level.txt
sas_prices_py-0.1.2.dist-info/RECORD
