Metadata-Version: 2.1
Name: sas-prices-py
Version: 0.1.2
Summary: Python package for fetching SAS flight prices
Home-page: https://github.com/alexechoi/sas-py
Author: Alex Choi
Author-email: alexchoidev@gmail.com
Classifier: Development Status :: 3 - Alpha
Classifier: Intended Audience :: Developers
Classifier: License :: OSI Approved :: MIT License
Classifier: Operating System :: OS Independent
Classifier: Programming Language :: Python :: 3
Classifier: Programming Language :: Python :: 3.7
Classifier: Programming Language :: Python :: 3.8
Classifier: Programming Language :: Python :: 3.9
Classifier: Programming Language :: Python :: 3.10
Requires-Python: >=3.7
License-File: LICENSE
Requires-Dist: requests>=2.32.3
Requires-Dist: aiohttp>=3.11.7
Requires-Dist: brotli>=1.1.0
